{
  "results": [
    {
      "title": "Education Portal",
      "url": "https://eduportal.cg.nic.in/ConsolidatedRpt.aspx?flag=DBC_S&dist=2205&blk=220523&clu=2205230025&sch=&psups=0",
      "snippet": "KARRI, GOVT PRIMARY SCHOOL SADHA MAR(22052300401). 3, KORBA, PONDI-UPRODA, KARRI, GOVT PRIMARY SCHOOL BAHRI JHORKI(22052300501). 4, KORBA, PONDI-UPRODA, KARRI ..."
    },
    {
      "title": "Dept. of Food",
      "url": "https://khadya.cg.nic.in/pdsonline/pmuy/RptApplinD.aspx?Id=1&DistrictID=20&TehsilID=008&UR=R&Code=0028",
      "snippet": "ODAGI ODAGI ODAGI KARRI INDARPUR 497231, INDARPUR HP GAS GRAMIN VITRAK. 6, 19220200800960000016000055002, MRSSUNITA, KARRI833330735967 WO AMAR SAY SARAS TAL ..."
    },
    {
      "title": "Education Portal",
      "url": "https://eduportal.cg.nic.in/ConsolidatedRpt.aspx?flag=DBC_S&dist=2205&blk=220523&clu=2205230025&sch=&psups=4",
      "snippet": "SrNo, District, Block, Cluster, School. 1, KORBA, PONDI-UPRODA, KARRI, GOVT MIDDLE SCHOOL KARRI(22052300802). 2, KORBA, PONDI-UPRODA, KARRI ..."
    },
    {
      "title": "Dept. of Food",
      "url": "https://khadya.cg.nic.in/pdsonline/pmuy/RptApplinD.aspx?Id=1&DistrictID=19&TehsilID=002&UR=R&Code=0021",
      "snippet": "20, 37220200200270000004400014003, MANMETSONHA, 54, 54BL:BALRAMPUR,VL:KARRI CHALGALI 54 KHAS KHAS KARRICHALGALI 497223, BALRAMPUR INDANE GRAMIN VITRAK ; 21 ..."
    },
    {
      "title": "Geo Tagged Asset Report",
      "url": "https://egramswaraj.gov.in/geotaggedforgpdp.do?planunttypcd=3&gpcode=85934",
      "snippet": "2021-11-16 15:27:39.969952. 2, 54459117, GP karri ke paraspur me rangpal ke ghar se jagdish yadav ke ghar tak c c road nirmann evm ucchikaran, 249300 ..."
    },
    {
      "title": "Dept. of Food",
      "url": "https://khadya.cg.nic.in/pdsonline/pmuy/RptEXBenefD.aspx?Vlocation=55030100008085&Action_Type=0",
      "snippet": "POST- KARRI POST- KARRI POST- KARRI 101137 KOTMI 495118, ABHINAV HP GAS GRAMIN VITRAK. 5, 618173, 09/01/2019, BHADRI BAI, WO SANTLAL CHANDRAUTHI CHANDRAUTHI ..."
    },
    {
      "title": "Dept. of Food",
      "url": "https://khadya.cg.nic.in/pdsonline/pmuy/RptApplinD.aspx?Id=1&DistrictID=05&TehsilID=002&UR=R&Code=0080",
      "snippet": "PASAN INDANE GRAMIN VITRAK. 67, 21220500200900000015100180005, BRIHASPATIYA, KARRI KARRI KARRI SARISMAR KOTMI 495119, ABHINAV HP GAS GRAMIN VITRAK. 68 ..."
    },
    {
      "title": "Dept. of Food",
      "url": "https://khadya.cg.nic.in/pdsonline/pmuy/RptEXBenefD.aspx?Vlocation=39050200000138&Action_Type=0",
      "snippet": "उज्जवला योजना के अंतर्गत 200 रु. में गैस कनैक्शन एवं नि:शुल्क डबल बर्नर स्टोव व प्रथम सिलेण्डर के जिला-बलरामपुर , विकासखंड-बलरामपुर, ग्रामपंचायत-कर्रीचलगली, ग्राम-कर्रीचलगली में लाभान्वितों की जानकारी ..."
    },
    {
      "title": "Education Portal",
      "url": "https://eduportal.cg.nic.in/ConsolidatedRpt.aspx?flag=DBC_S&dist=2226&blk=222610&clu=2226100116&sch=&psups=0",
      "snippet": "KARRI(22261009102). 17, BALRAMPUR, BALRAMPUR, RANHAT, P.S. KUSUMKONA(22261009103). 18, BALRAMPUR, BALRAMPUR, RANHAT, GOVT. HIGH SCHOOL KARRI(22261009104). 19 ..."
    },
    {
      "title": "Dept. of Food",
      "url": "http://khadya.cg.nic.in/pdsonline/pmuy/RptBenefD.aspx?Id=3&DistrictID=01&TehsilID=001&UR=R&Code=0059",
      "snippet": "SVITRI HOUSE, 58 BL:BHARATPUR,VL:PO 4 KARRI ROD CHHIRHATOLA CHHIRHATOLA 497778, JANAKPUR INDANE GRAMIN VITRAK. 118, 7063949063, 24/03/2018, SEM BAI, SEMBAI ..."
    }
  ]
}